file_util_adriangassen/__init__.py
file_util_adriangassen/__main__.py
file_util_adriangassen/cli.py
file_util_adriangassen/combine.py
file_util_adriangassen/cp.py
file_util_adriangassen/create.py
file_util_adriangassen/remove.py
file_util_adriangassen/utils.py
file_util_adriangassen-1.0.0.dist-info/licenses/LICENSE.txt
file_util_adriangassen-1.0.0.dist-info/METADATA
file_util_adriangassen-1.0.0.dist-info/WHEEL
file_util_adriangassen-1.0.0.dist-info/entry_points.txt
file_util_adriangassen-1.0.0.dist-info/top_level.txt
file_util_adriangassen-1.0.0.dist-info/RECORD
