Metadata-Version: 2.4
Name: file_util_adriangassen
Version: 1.0.0
Summary: A simple file utility
Author-email: Adrian Gassen <a.m.gassen@icloud.com>
License-Expression: MIT
Project-URL: Repository, https://gitlab.com/adriangassen/file-util
License-File: LICENSE.txt
Provides-Extra: dev
Requires-Dist: pytest; extra == "dev"
Dynamic: license-file
